kheops/__init__.py
kheops/core.py
kheops/utils.py
kheops-0.2.dist-info/METADATA
kheops-0.2.dist-info/WHEEL
kheops-0.2.dist-info/top_level.txt
kheops-0.2.dist-info/RECORD
